<?xml version="1.0" encoding="utf-8"?>
<Defs>
  <ThingDef ParentName="BaseBullet">
    <defName>Bullet_LAMG_21CA</defName>
    <label>KAC LAMG bullet</label>
    <graphicData>
      <texPath>Things/Projectile/Bullet_Small</texPath>
      <graphicClass>Graphic_Single</graphicClass>
      <drawSize>1.15</drawSize>
    </graphicData>
    <projectile>
      <damageDef>Bullet</damageDef>
      <damageAmountBase>11</damageAmountBase>
      <speed>83</speed>
    </projectile>
  </ThingDef>
  <ThingDef ParentName="BaseHumanMakeableGun">
    <defName>Axi_LMG_LAMG_21CA</defName>
    <label>Knight's Armament LAMG</label>
    <description>Knight's Armament Company has long been known for boutique-quality assault and precision rifles, but the LAMG is something of a passion project for KAC's engineers. Having spent over 40 years in various states and stages of development, the LAMG finally came to market in the service of Amurcan special operations forces. While it's rate of fire and per-round stopping power aren't anything to write home about, the accuracy and mild recoil impulse it achieves are another matter entirely. Capable of being fired with one hand, as shown in a string of notable demonstrations, the LAMG is truly a masterpiece of suppressive firepower.</description>
    <graphicData>
      <texPath>Things/LMG_LAMG</texPath>
      <graphicClass>Graphic_Single</graphicClass>
      <drawSize>1.15</drawSize>
    </graphicData>
    <soundInteract>Interact_Rifle</soundInteract>
    <statBases>
      <WorkToMake>45000</WorkToMake>
      <Mass>6.5</Mass>
      <AccuracyTouch>.5</AccuracyTouch>
      <AccuracyShort>.65</AccuracyShort>
      <AccuracyMedium>.55</AccuracyMedium>
      <AccuracyLong>.4</AccuracyLong>
      <RangedWeapon_Cooldown>1.4</RangedWeapon_Cooldown>
    </statBases>
    <recipeMaker>
      <researchPrerequisite>GasOperation</researchPrerequisite>
      <skillRequirements>
        <Crafting>6</Crafting>
      </skillRequirements>
    </recipeMaker>
    <costList>
      <Steel>85</Steel>
      <ComponentIndustrial>6</ComponentIndustrial>
    </costList>
    <verbs>
      <li>
        <verbClass>Verb_Shoot</verbClass>
        <hasStandardCommand>true</hasStandardCommand>
        <defaultProjectile>Bullet_LAMG_21CA</defaultProjectile>
        <warmupTime>1.4</warmupTime>
        <range>30</range>
        <burstShotCount>6</burstShotCount>
        <ticksBetweenBurstShots>10</ticksBetweenBurstShots>
        <soundCast>Shot_Minigun</soundCast>
        <soundCastTail>GunTail_Heavy</soundCastTail>
        <muzzleFlashScale>10</muzzleFlashScale>
      </li>
    </verbs>
    <tools>
      <li>
        <label>stock</label>
        <capacities>
          <li>Blunt</li>
        </capacities>
        <power>8</power>
        <cooldownTime>1.6</cooldownTime>
      </li>
      <li>
        <label>barrel</label>
        <capacities>
          <li>Blunt</li>
          <li>Poke</li>
        </capacities>
        <power>8</power>
        <cooldownTime>1.6</cooldownTime>
      </li>
    </tools>
  </ThingDef>
</Defs>
